{
    "problems": [
        {
            "Q": "5+5",
            "A":   ["10","ten","десять"],
            "V": ["10","ten","десять","1O"]
        },
        {
            "Q": "7+3",
            "A":   ["10","десять","ten"],
            "V":["10","ten","десять","4"]
        },
        {
            "Q": "1+1",
            "A":   ["2","два","two"],
            "V":["2","11","два","two"]
        },
        {
            "Q": "8+3",
            "A":   ["eleven","11","одиннадцать"],
            "V":["eleven","11","одиннадцать","5"]
        },
        {
            "Q": "1+2",
            "A":  ["три","three","3","III"],
            "V":["три","three","3","III","з"]
        }
    ]
}